[
  {
    "id": "ck-mYVzme2fybU-0",
    "episodeId": "mYVzme2fybU",
    "chunkId": "ck-mYVzme2fybU-0",
    "text": "This is a pivotal moment in American history, and what happens now will determine the lives of our kids and future generations.",
    "score": 60,
    "num": 0,
    "status": {
      "graph": false,
      "ready": true,
      "verified": false,
      "completed": false,
      "researched": false
    },
    "metadata": {
      "claim": {
        "text": "This is a pivotal moment in American history, and what happens now will determine the lives of our kids and future generations.",
        "score": 60
      }
    },
    "graph": null,
    "createdAt": "2025-07-02T05:18:01.037Z",
    "updatedAt": "2025-07-02T05:18:01.037Z"
  },
  {
    "id": "ck-mYVzme2fybU-1",
    "episodeId": "mYVzme2fybU",
    "chunkId": "ck-mYVzme2fybU-1",
    "text": "America today has more income and wealth inequality than ever before in the history of the country.",
    "score": 85,
    "num": 1,
    "status": {
      "graph": false,
      "ready": true,
      "verified": false,
      "completed": false,
      "researched": false
    },
    "metadata": {
      "claim": {
        "text": "America today has more income and wealth inequality than ever before in the history of the country.",
        "score": 85
      }
    },
    "graph": null,
    "createdAt": "2025-07-02T05:18:00.929Z",
    "updatedAt": "2025-07-02T05:18:00.929Z"
  },
  {
    "id": "ck-mYVzme2fybU-2",
    "episodeId": "mYVzme2fybU",
    "chunkId": "ck-mYVzme2fybU-2",
    "text": "CEOs of large corporations are making 350 times what their workers make, highlighting economic disparity.",
    "score": 20,
    "num": 2,
    "status": {
      "graph": false,
      "ready": true,
      "verified": false,
      "completed": false,
      "researched": false
    },
    "metadata": {
      "claim": {
        "text": "CEOs of large corporations are making 350 times what their workers make, highlighting economic disparity.",
        "score": 20
      }
    },
    "graph": null,
    "createdAt": "2025-07-02T05:18:00.469Z",
    "updatedAt": "2025-07-02T05:18:00.469Z"
  },
  {
    "id": "ck-mYVzme2fybU-3",
    "episodeId": "mYVzme2fybU",
    "chunkId": "ck-mYVzme2fybU-3",
    "text": "Many people lack a thousand dollars in savings, making unexpected expenses like car repairs financially devastating.",
    "score": 60,
    "num": 3,
    "status": {
      "graph": false,
      "ready": true,
      "verified": false,
      "completed": false,
      "researched": false
    },
    "metadata": {
      "claim": {
        "text": "Many people lack a thousand dollars in savings, making unexpected expenses like car repairs financially devastating.",
        "score": 60
      }
    },
    "graph": null,
    "createdAt": "2025-07-02T05:18:01.008Z",
    "updatedAt": "2025-07-02T05:18:01.008Z"
  },
  {
    "id": "ck-mYVzme2fybU-4",
    "episodeId": "mYVzme2fybU",
    "chunkId": "ck-mYVzme2fybU-4",
    "text": "The national minimum wage in Washington is $7.25 an hour, and millions of workers make $10-13 an hour.",
    "score": 20,
    "num": 4,
    "status": {
      "graph": false,
      "ready": true,
      "verified": false,
      "completed": false,
      "researched": false
    },
    "metadata": {
      "claim": {
        "text": "The national minimum wage in Washington is $7.25 an hour, and millions of workers make $10-13 an hour.",
        "score": 20
      }
    },
    "graph": null,
    "createdAt": "2025-07-02T05:18:00.930Z",
    "updatedAt": "2025-07-02T05:18:00.930Z"
  },
  {
    "id": "ck-mYVzme2fybU-5",
    "episodeId": "mYVzme2fybU",
    "chunkId": "ck-mYVzme2fybU-5",
    "text": "Corporations have gotten rid of defined benefit pension plans, leaving many older workers with nothing saved for retirement.",
    "score": 20,
    "num": 5,
    "status": {
      "graph": false,
      "ready": true,
      "verified": false,
      "completed": false,
      "researched": false
    },
    "metadata": {
      "claim": {
        "text": "Corporations have gotten rid of defined benefit pension plans, leaving many older workers with nothing saved for retirement.",
        "score": 20
      }
    },
    "graph": null,
    "createdAt": "2025-07-02T05:18:00.931Z",
    "updatedAt": "2025-07-02T05:18:00.931Z"
  },
  {
    "id": "ck-mYVzme2fybU-6",
    "episodeId": "mYVzme2fybU",
    "chunkId": "ck-mYVzme2fybU-6",
    "text": "Huge conglomerates own the world, and they don't care about the needs of working people.",
    "score": 80,
    "num": 6,
    "status": {
      "graph": false,
      "ready": true,
      "verified": false,
      "completed": false,
      "researched": false
    },
    "metadata": {
      "claim": {
        "text": "Huge conglomerates own the world, and they don't care about the needs of working people.",
        "score": 80
      }
    },
    "graph": null,
    "createdAt": "2025-07-02T05:18:00.401Z",
    "updatedAt": "2025-07-02T05:18:00.401Z"
  },
  {
    "id": "ck-mYVzme2fybU-7",
    "episodeId": "mYVzme2fybU",
    "chunkId": "ck-mYVzme2fybU-7",
    "text": "The healthcare system in America is not working, as evidenced by the celebration following the assassination of a United Healthcare executive.",
    "score": 70,
    "num": 7,
    "status": {
      "graph": false,
      "ready": true,
      "verified": false,
      "completed": false,
      "researched": false
    },
    "metadata": {
      "claim": {
        "text": "The healthcare system in America is not working, as evidenced by the celebration following the assassination of a United Healthcare executive.",
        "score": 70
      }
    },
    "graph": null,
    "createdAt": "2025-07-02T05:18:00.931Z",
    "updatedAt": "2025-07-02T05:18:00.931Z"
  },
  {
    "id": "ck-mYVzme2fybU-8",
    "episodeId": "mYVzme2fybU",
    "chunkId": "ck-mYVzme2fybU-8",
    "text": "Insurance companies make it difficult for people to get money from them, as the more they deny, the more money they make.",
    "score": 80,
    "num": 8,
    "status": {
      "graph": false,
      "ready": true,
      "verified": false,
      "completed": false,
      "researched": false
    },
    "metadata": {
      "claim": {
        "text": "Insurance companies make it difficult for people to get money from them, as the more they deny, the more money they make.",
        "score": 80
      }
    },
    "graph": null,
    "createdAt": "2025-07-02T05:18:00.928Z",
    "updatedAt": "2025-07-02T05:18:00.928Z"
  },
  {
    "id": "ck-mYVzme2fybU-9",
    "episodeId": "mYVzme2fybU",
    "chunkId": "ck-mYVzme2fybU-9",
    "text": "The top 1% now owns more wealth than the bottom 93% and millions of people struggle in America.",
    "score": 60,
    "num": 9,
    "status": {
      "graph": false,
      "ready": true,
      "verified": false,
      "completed": false,
      "researched": false
    },
    "metadata": {
      "claim": {
        "text": "The top 1% now owns more wealth than the bottom 93% and millions of people struggle in America.",
        "score": 60
      }
    },
    "graph": null,
    "createdAt": "2025-07-02T05:18:01.458Z",
    "updatedAt": "2025-07-02T05:18:01.458Z"
  },
  {
    "id": "ck-mYVzme2fybU-10",
    "episodeId": "mYVzme2fybU",
    "chunkId": "ck-mYVzme2fybU-10",
    "text": "The Supreme Court's decision is the worst decision the court has ever made.",
    "score": 60,
    "num": 10,
    "status": {
      "graph": false,
      "ready": true,
      "verified": false,
      "completed": false,
      "researched": false
    },
    "metadata": {
      "claim": {
        "text": "The Supreme Court's decision is the worst decision the court has ever made.",
        "score": 60
      }
    },
    "graph": null,
    "createdAt": "2025-07-02T05:18:04.596Z",
    "updatedAt": "2025-07-02T05:18:04.596Z"
  },
  {
    "id": "ck-mYVzme2fybU-11",
    "episodeId": "mYVzme2fybU",
    "chunkId": "ck-mYVzme2fybU-11",
    "text": "During the election, it wasn't just Musk and Republicans putting a lot of money into Trump.",
    "score": 80,
    "num": 11,
    "status": {
      "graph": false,
      "ready": true,
      "verified": false,
      "completed": false,
      "researched": false
    },
    "metadata": {
      "claim": {
        "text": "During the election, it wasn't just Musk and Republicans putting a lot of money into Trump.",
        "score": 80
      }
    },
    "graph": null,
    "createdAt": "2025-07-02T05:18:07.223Z",
    "updatedAt": "2025-07-02T05:18:07.223Z"
  },
  {
    "id": "ck-mYVzme2fybU-12",
    "episodeId": "mYVzme2fybU",
    "chunkId": "ck-mYVzme2fybU-12",
    "text": "The corrupt campaign finance system on both sides is rejecting the will of the American people and supporting special interests.",
    "score": 60,
    "num": 12,
    "status": {
      "graph": false,
      "ready": true,
      "verified": false,
      "completed": false,
      "researched": false
    },
    "metadata": {
      "claim": {
        "text": "The corrupt campaign finance system on both sides is rejecting the will of the American people and supporting special interests.",
        "score": 60
      }
    },
    "graph": null,
    "createdAt": "2025-07-02T05:18:06.694Z",
    "updatedAt": "2025-07-02T05:18:06.694Z"
  },
  {
    "id": "ck-mYVzme2fybU-13",
    "episodeId": "mYVzme2fybU",
    "chunkId": "ck-mYVzme2fybU-13",
    "text": "The current healthcare system functions to make insurance and drug companies very rich, and it works.",
    "score": 75,
    "num": 13,
    "status": {
      "graph": false,
      "ready": true,
      "verified": false,
      "completed": false,
      "researched": false
    },
    "metadata": {
      "claim": {
        "text": "The current healthcare system functions to make insurance and drug companies very rich, and it works.",
        "score": 75
      }
    },
    "graph": null,
    "createdAt": "2025-07-02T05:18:07.222Z",
    "updatedAt": "2025-07-02T05:18:07.222Z"
  },
  {
    "id": "ck-mYVzme2fybU-14",
    "episodeId": "mYVzme2fybU",
    "chunkId": "ck-mYVzme2fybU-14",
    "text": "If you want to make America great again, less losers.",
    "score": 75,
    "num": 14,
    "status": {
      "graph": false,
      "ready": true,
      "verified": false,
      "completed": false,
      "researched": false
    },
    "metadata": {
      "claim": {
        "text": "If you want to make America great again, less losers.",
        "score": 75
      }
    },
    "graph": null,
    "createdAt": "2025-07-02T05:18:06.692Z",
    "updatedAt": "2025-07-02T05:18:06.692Z"
  },
  {
    "id": "ck-mYVzme2fybU-15",
    "episodeId": "mYVzme2fybU",
    "chunkId": "ck-mYVzme2fybU-15",
    "text": "The cost of childcare, housing, healthcare, education, and food are too high for many families to afford.",
    "score": 75,
    "num": 15,
    "status": {
      "graph": false,
      "ready": true,
      "verified": false,
      "completed": false,
      "researched": false
    },
    "metadata": {
      "claim": {
        "text": "The cost of childcare, housing, healthcare, education, and food are too high for many families to afford.",
        "score": 75
      }
    },
    "graph": null,
    "createdAt": "2025-07-02T05:18:06.802Z",
    "updatedAt": "2025-07-02T05:18:06.802Z"
  },
  {
    "id": "ck-mYVzme2fybU-16",
    "episodeId": "mYVzme2fybU",
    "chunkId": "ck-mYVzme2fybU-16",
    "text": "The financial difficulties of supporting a family led to both parents needing to work to stay afloat financially.",
    "score": 85,
    "num": 16,
    "status": {
      "graph": false,
      "ready": true,
      "verified": false,
      "completed": false,
      "researched": false
    },
    "metadata": {
      "claim": {
        "text": "The financial difficulties of supporting a family led to both parents needing to work to stay afloat financially.",
        "score": 85
      }
    },
    "graph": null,
    "createdAt": "2025-07-02T05:18:06.694Z",
    "updatedAt": "2025-07-02T05:18:06.694Z"
  },
  {
    "id": "ck-mYVzme2fybU-17",
    "episodeId": "mYVzme2fybU",
    "chunkId": "ck-mYVzme2fybU-17",
    "text": "Ain't nobody in America today who's paid 18% of their salary for rent, which is what the speaker's family paid.",
    "score": 90,
    "num": 17,
    "status": {
      "graph": false,
      "ready": true,
      "verified": false,
      "completed": false,
      "researched": false
    },
    "metadata": {
      "claim": {
        "text": "Ain't nobody in America today who's paid 18% of their salary for rent, which is what the speaker's family paid.",
        "score": 90
      }
    },
    "graph": null,
    "createdAt": "2025-07-02T05:18:06.705Z",
    "updatedAt": "2025-07-02T05:18:06.705Z"
  },
  {
    "id": "ck-mYVzme2fybU-18",
    "episodeId": "mYVzme2fybU",
    "chunkId": "ck-mYVzme2fybU-18",
    "text": "Childcare workers make $15 an hour, while families struggle to afford childcare, costing around $20,000 annually in some states.",
    "score": 60,
    "num": 18,
    "status": {
      "graph": false,
      "ready": true,
      "verified": false,
      "completed": false,
      "researched": false
    },
    "metadata": {
      "claim": {
        "text": "Childcare workers make $15 an hour, while families struggle to afford childcare, costing around $20,000 annually in some states.",
        "score": 60
      }
    },
    "graph": null,
    "createdAt": "2025-07-02T05:18:07.365Z",
    "updatedAt": "2025-07-02T05:18:07.365Z"
  },
  {
    "id": "ck-mYVzme2fybU-19",
    "episodeId": "mYVzme2fybU",
    "chunkId": "ck-mYVzme2fybU-19",
    "text": "America's healthcare system is failing because it is based on greed, not on need, and there is a shortage of doctors.",
    "score": 60,
    "num": 19,
    "status": {
      "graph": false,
      "ready": true,
      "verified": false,
      "completed": false,
      "researched": false
    },
    "metadata": {
      "claim": {
        "text": "America's healthcare system is failing because it is based on greed, not on need, and there is a shortage of doctors.",
        "score": 60
      }
    },
    "graph": null,
    "createdAt": "2025-07-02T05:18:07.223Z",
    "updatedAt": "2025-07-02T05:18:07.223Z"
  },
  {
    "id": "ck-mYVzme2fybU-20",
    "episodeId": "mYVzme2fybU",
    "chunkId": "ck-mYVzme2fybU-20",
    "text": "It is not unusual for people from working-class homes to go to medical school and come out $500,000 in debt.",
    "score": 60,
    "num": 20,
    "status": {
      "graph": false,
      "ready": true,
      "verified": false,
      "completed": false,
      "researched": false
    },
    "metadata": {
      "claim": {
        "text": "It is not unusual for people from working-class homes to go to medical school and come out $500,000 in debt.",
        "score": 60
      }
    },
    "graph": null,
    "createdAt": "2025-07-02T05:18:09.342Z",
    "updatedAt": "2025-07-02T05:18:09.342Z"
  },
  {
    "id": "ck-mYVzme2fybU-21",
    "episodeId": "mYVzme2fybU",
    "chunkId": "ck-mYVzme2fybU-21",
    "text": "We need more doctors, and the speaker encourages someone to go to medical school with tuition assistance.",
    "score": 60,
    "num": 21,
    "status": {
      "graph": false,
      "ready": true,
      "verified": false,
      "completed": false,
      "researched": false
    },
    "metadata": {
      "claim": {
        "text": "We need more doctors, and the speaker encourages someone to go to medical school with tuition assistance.",
        "score": 60
      }
    },
    "graph": null,
    "createdAt": "2025-07-02T05:18:10.914Z",
    "updatedAt": "2025-07-02T05:18:10.914Z"
  },
  {
    "id": "ck-mYVzme2fybU-22",
    "episodeId": "mYVzme2fybU",
    "chunkId": "ck-mYVzme2fybU-22",
    "text": "Public funding of elections would prevent candidates from receiving money from super PACs and other sources.",
    "score": 60,
    "num": 22,
    "status": {
      "graph": false,
      "ready": true,
      "verified": false,
      "completed": false,
      "researched": false
    },
    "metadata": {
      "claim": {
        "text": "Public funding of elections would prevent candidates from receiving money from super PACs and other sources.",
        "score": 60
      }
    },
    "graph": null,
    "createdAt": "2025-07-02T05:18:11.936Z",
    "updatedAt": "2025-07-02T05:18:11.936Z"
  },
  {
    "id": "ck-mYVzme2fybU-23",
    "episodeId": "mYVzme2fybU",
    "chunkId": "ck-mYVzme2fybU-23",
    "text": "Public funding for campaigns, where candidates receive a set amount of money, exists in New York City and other places.",
    "score": 75,
    "num": 23,
    "status": {
      "graph": false,
      "ready": true,
      "verified": false,
      "completed": false,
      "researched": false
    },
    "metadata": {
      "claim": {
        "text": "Public funding for campaigns, where candidates receive a set amount of money, exists in New York City and other places.",
        "score": 75
      }
    },
    "graph": null,
    "createdAt": "2025-07-02T05:18:11.938Z",
    "updatedAt": "2025-07-02T05:18:11.938Z"
  },
  {
    "id": "ck-mYVzme2fybU-24",
    "episodeId": "mYVzme2fybU",
    "chunkId": "ck-mYVzme2fybU-24",
    "text": "The speaker believes that the majority of polls are inaccurate and unreliable in predicting election outcomes.",
    "score": 60,
    "num": 24,
    "status": {
      "graph": false,
      "ready": true,
      "verified": false,
      "completed": false,
      "researched": false
    },
    "metadata": {
      "claim": {
        "text": "The speaker believes that the majority of polls are inaccurate and unreliable in predicting election outcomes.",
        "score": 60
      }
    },
    "graph": null,
    "createdAt": "2025-07-02T05:18:12.048Z",
    "updatedAt": "2025-07-02T05:18:12.048Z"
  },
  {
    "id": "ck-mYVzme2fybU-25",
    "episodeId": "mYVzme2fybU",
    "chunkId": "ck-mYVzme2fybU-25",
    "text": "The very rich paid at their upper levels 90% under Eisenhower, but that is not across the board.",
    "score": 1,
    "num": 25,
    "status": {
      "graph": false,
      "ready": true,
      "verified": false,
      "completed": false,
      "researched": false
    },
    "metadata": {
      "claim": {
        "text": "The very rich paid at their upper levels 90% under Eisenhower, but that is not across the board.",
        "score": 1.23
      }
    },
    "graph": null,
    "createdAt": "2025-07-02T05:18:12.555Z",
    "updatedAt": "2025-07-02T05:18:12.555Z"
  },
  {
    "id": "ck-mYVzme2fybU-26",
    "episodeId": "mYVzme2fybU",
    "chunkId": "ck-mYVzme2fybU-26",
    "text": "The Earth is currently in a cooling period, according to a Washington Post article analyzing long-term climate data.",
    "score": 30,
    "num": 26,
    "status": {
      "graph": false,
      "ready": true,
      "verified": false,
      "completed": false,
      "researched": false
    },
    "metadata": {
      "claim": {
        "text": "The Earth is currently in a cooling period, according to a Washington Post article analyzing long-term climate data.",
        "score": 30
      }
    },
    "graph": null,
    "createdAt": "2025-07-02T05:18:12.986Z",
    "updatedAt": "2025-07-02T05:18:12.986Z"
  },
  {
    "id": "ck-mYVzme2fybU-27",
    "episodeId": "mYVzme2fybU",
    "chunkId": "ck-mYVzme2fybU-27",
    "text": "Climate change is being used by powerful entities to gain more control over citizens through measures like carbon taxes and travel restrictions.",
    "score": 20,
    "num": 27,
    "status": {
      "graph": false,
      "ready": true,
      "verified": false,
      "completed": false,
      "researched": false
    },
    "metadata": {
      "claim": {
        "text": "Climate change is being used by powerful entities to gain more control over citizens through measures like carbon taxes and travel restrictions.",
        "score": 20
      }
    },
    "graph": null,
    "createdAt": "2025-07-02T05:18:13.509Z",
    "updatedAt": "2025-07-02T05:18:13.509Z"
  },
  {
    "id": "ck-mYVzme2fybU-28",
    "episodeId": "mYVzme2fybU",
    "chunkId": "ck-mYVzme2fybU-28",
    "text": "We're killing all the fish in the ocean and sucking them out in giant numbers.",
    "score": 10,
    "num": 28,
    "status": {
      "graph": false,
      "ready": true,
      "verified": false,
      "completed": false,
      "researched": false
    },
    "metadata": {
      "claim": {
        "text": "We're killing all the fish in the ocean and sucking them out in giant numbers.",
        "score": 10
      }
    },
    "graph": null,
    "createdAt": "2025-07-02T05:18:11.434Z",
    "updatedAt": "2025-07-02T05:18:11.434Z"
  },
  {
    "id": "ck-mYVzme2fybU-29",
    "episodeId": "mYVzme2fybU",
    "chunkId": "ck-mYVzme2fybU-29",
    "text": "Native Americans respected nature, understanding that killing off the buffalo would have consequences.",
    "score": 60,
    "num": 29,
    "status": {
      "graph": false,
      "ready": true,
      "verified": false,
      "completed": false,
      "researched": false
    },
    "metadata": {
      "claim": {
        "text": "Native Americans respected nature, understanding that killing off the buffalo would have consequences.",
        "score": 60
      }
    },
    "graph": null,
    "createdAt": "2025-07-02T05:18:11.951Z",
    "updatedAt": "2025-07-02T05:18:11.951Z"
  },
  {
    "id": "ck-mYVzme2fybU-30",
    "episodeId": "mYVzme2fybU",
    "chunkId": "ck-mYVzme2fybU-30",
    "text": "If you lose that harmony, I worry about the future of humanity, which is the problem with financial competitiveness.",
    "score": 60,
    "num": 30,
    "status": {
      "graph": false,
      "ready": true,
      "verified": false,
      "completed": false,
      "researched": false
    },
    "metadata": {
      "claim": {
        "text": "If you lose that harmony, I worry about the future of humanity, which is the problem with financial competitiveness.",
        "score": 60
      }
    },
    "graph": null,
    "createdAt": "2025-07-02T05:18:14.557Z",
    "updatedAt": "2025-07-02T05:18:14.557Z"
  },
  {
    "id": "ck-mYVzme2fybU-31",
    "episodeId": "mYVzme2fybU",
    "chunkId": "ck-mYVzme2fybU-31",
    "text": "In real inflation accounted for dollars, wages are actually lower now than they were 52 years ago.",
    "score": 20,
    "num": 31,
    "status": {
      "graph": false,
      "ready": true,
      "verified": false,
      "completed": false,
      "researched": false
    },
    "metadata": {
      "claim": {
        "text": "In real inflation accounted for dollars, wages are actually lower now than they were 52 years ago.",
        "score": 20
      }
    },
    "graph": null,
    "createdAt": "2025-07-02T05:18:16.653Z",
    "updatedAt": "2025-07-02T05:18:16.653Z"
  },
  {
    "id": "ck-mYVzme2fybU-32",
    "episodeId": "mYVzme2fybU",
    "chunkId": "ck-mYVzme2fybU-32",
    "text": "Most Americans believe their situation is worse today than it was 40 years ago, despite technological advancements.",
    "score": 60,
    "num": 32,
    "status": {
      "graph": false,
      "ready": true,
      "verified": false,
      "completed": false,
      "researched": false
    },
    "metadata": {
      "claim": {
        "text": "Most Americans believe their situation is worse today than it was 40 years ago, despite technological advancements.",
        "score": 60
      }
    },
    "graph": null,
    "createdAt": "2025-07-02T05:18:17.191Z",
    "updatedAt": "2025-07-02T05:18:17.191Z"
  },
  {
    "id": "ck-mYVzme2fybU-33",
    "episodeId": "mYVzme2fybU",
    "chunkId": "ck-mYVzme2fybU-33",
    "text": "The minimum wage in this country is ridiculous, and it is insane to live off of $7 an hour.",
    "score": 95,
    "num": 33,
    "status": {
      "graph": false,
      "ready": true,
      "verified": false,
      "completed": false,
      "researched": false
    },
    "metadata": {
      "claim": {
        "text": "The minimum wage in this country is ridiculous, and it is insane to live off of $7 an hour.",
        "score": 95
      }
    },
    "graph": null,
    "createdAt": "2025-07-02T05:18:17.707Z",
    "updatedAt": "2025-07-02T05:18:17.707Z"
  },
  {
    "id": "ck-mYVzme2fybU-34",
    "episodeId": "mYVzme2fybU",
    "chunkId": "ck-mYVzme2fybU-34",
    "text": "Raising the federal minimum wage to $17 an hour is a reasonable amount of money, according to the speaker.",
    "score": 70,
    "num": 34,
    "status": {
      "graph": false,
      "ready": true,
      "verified": false,
      "completed": false,
      "researched": false
    },
    "metadata": {
      "claim": {
        "text": "Raising the federal minimum wage to $17 an hour is a reasonable amount of money, according to the speaker.",
        "score": 70
      }
    },
    "graph": null,
    "createdAt": "2025-07-02T05:18:17.703Z",
    "updatedAt": "2025-07-02T05:18:17.703Z"
  },
  {
    "id": "ck-mYVzme2fybU-35",
    "episodeId": "mYVzme2fybU",
    "chunkId": "ck-mYVzme2fybU-35",
    "text": "Technology and unchecked use of it has accentuated self harm, suicide, suicidal ideiology, depression, and anxiety.",
    "score": 60,
    "num": 35,
    "status": {
      "graph": false,
      "ready": true,
      "verified": false,
      "completed": false,
      "researched": false
    },
    "metadata": {
      "claim": {
        "text": "Technology and unchecked use of it has accentuated self harm, suicide, suicidal ideiology, depression, and anxiety.",
        "score": 60
      }
    },
    "graph": null,
    "createdAt": "2025-07-02T05:18:17.706Z",
    "updatedAt": "2025-07-02T05:18:17.706Z"
  },
  {
    "id": "ck-mYVzme2fybU-36",
    "episodeId": "mYVzme2fybU",
    "chunkId": "ck-mYVzme2fybU-36",
    "text": "Massive automation of jobs is a problem, especially for corporations focused on maximizing profit.",
    "score": 60,
    "num": 36,
    "status": {
      "graph": false,
      "ready": true,
      "verified": false,
      "completed": false,
      "researched": false
    },
    "metadata": {
      "claim": {
        "text": "Massive automation of jobs is a problem, especially for corporations focused on maximizing profit.",
        "score": 60
      }
    },
    "graph": null,
    "createdAt": "2025-07-02T05:18:18.228Z",
    "updatedAt": "2025-07-02T05:18:18.228Z"
  },
  {
    "id": "ck-mYVzme2fybU-37",
    "episodeId": "mYVzme2fybU",
    "chunkId": "ck-mYVzme2fybU-37",
    "text": "Artificial intelligence is going to displace millions and millions of workers, and they will be thrown out on the street.",
    "score": 70,
    "num": 37,
    "status": {
      "graph": false,
      "ready": true,
      "verified": false,
      "completed": false,
      "researched": false
    },
    "metadata": {
      "claim": {
        "text": "Artificial intelligence is going to displace millions and millions of workers, and they will be thrown out on the street.",
        "score": 70
      }
    },
    "graph": null,
    "createdAt": "2025-07-02T05:18:18.227Z",
    "updatedAt": "2025-07-02T05:18:18.227Z"
  },
  {
    "id": "ck-mYVzme2fybU-38",
    "episodeId": "mYVzme2fybU",
    "chunkId": "ck-mYVzme2fybU-38",
    "text": "Ford and corporate America have the right to tell workers throughout the country, hey, sorry guys, we don't need you anymore.",
    "score": 60,
    "num": 38,
    "status": {
      "graph": false,
      "ready": true,
      "verified": false,
      "completed": false,
      "researched": false
    },
    "metadata": {
      "claim": {
        "text": "Ford and corporate America have the right to tell workers throughout the country, hey, sorry guys, we don't need you anymore.",
        "score": 60
      }
    },
    "graph": null,
    "createdAt": "2025-07-02T05:18:18.228Z",
    "updatedAt": "2025-07-02T05:18:18.228Z"
  },
  {
    "id": "ck-mYVzme2fybU-39",
    "episodeId": "mYVzme2fybU",
    "chunkId": "ck-mYVzme2fybU-39",
    "text": "The country should deal with exploding technology so it benefits all and not just Ford and General Motors.",
    "score": 65,
    "num": 39,
    "status": {
      "graph": false,
      "ready": true,
      "verified": false,
      "completed": false,
      "researched": false
    },
    "metadata": {
      "claim": {
        "text": "The country should deal with exploding technology so it benefits all and not just Ford and General Motors.",
        "score": 65
      }
    },
    "graph": null,
    "createdAt": "2025-07-02T05:18:18.893Z",
    "updatedAt": "2025-07-02T05:18:18.893Z"
  },
  {
    "id": "ck-mYVzme2fybU-40",
    "episodeId": "mYVzme2fybU",
    "chunkId": "ck-mYVzme2fybU-40",
    "text": "If you had healthcare as a human right and not attached to your job, that would be a major step forward.",
    "score": 85,
    "num": 40,
    "status": {
      "graph": false,
      "ready": true,
      "verified": false,
      "completed": false,
      "researched": false
    },
    "metadata": {
      "claim": {
        "text": "If you had healthcare as a human right and not attached to your job, that would be a major step forward.",
        "score": 85
      }
    },
    "graph": null,
    "createdAt": "2025-07-02T05:18:20.325Z",
    "updatedAt": "2025-07-02T05:18:20.325Z"
  },
  {
    "id": "ck-mYVzme2fybU-41",
    "episodeId": "mYVzme2fybU",
    "chunkId": "ck-mYVzme2fybU-41",
    "text": "If it was profitable to wipe out poverty, which it should be, like overall as a community, less losers, higher GDP.",
    "score": 70,
    "num": 41,
    "status": {
      "graph": false,
      "ready": true,
      "verified": false,
      "completed": false,
      "researched": false
    },
    "metadata": {
      "claim": {
        "text": "If it was profitable to wipe out poverty, which it should be, like overall as a community, less losers, higher GDP.",
        "score": 70
      }
    },
    "graph": null,
    "createdAt": "2025-07-02T05:18:22.041Z",
    "updatedAt": "2025-07-02T05:18:22.041Z"
  },
  {
    "id": "ck-mYVzme2fybU-42",
    "episodeId": "mYVzme2fybU",
    "chunkId": "ck-mYVzme2fybU-42",
    "text": "Publicly funded healthcare systems guarantee healthcare to all people, which would lower the stress rate enormously.",
    "score": 75,
    "num": 42,
    "status": {
      "graph": false,
      "ready": true,
      "verified": false,
      "completed": false,
      "researched": false
    },
    "metadata": {
      "claim": {
        "text": "Publicly funded healthcare systems guarantee healthcare to all people, which would lower the stress rate enormously.",
        "score": 75
      }
    },
    "graph": null,
    "createdAt": "2025-07-02T05:18:22.507Z",
    "updatedAt": "2025-07-02T05:18:22.507Z"
  },
  {
    "id": "ck-mYVzme2fybU-43",
    "episodeId": "mYVzme2fybU",
    "chunkId": "ck-mYVzme2fybU-43",
    "text": "If I want this country to be productive, I want the best educated workforce.",
    "score": 85,
    "num": 43,
    "status": {
      "graph": false,
      "ready": true,
      "verified": false,
      "completed": false,
      "researched": false
    },
    "metadata": {
      "claim": {
        "text": "If I want this country to be productive, I want the best educated workforce.",
        "score": 85
      }
    },
    "graph": null,
    "createdAt": "2025-07-02T05:18:23.472Z",
    "updatedAt": "2025-07-02T05:18:23.472Z"
  },
  {
    "id": "ck-mYVzme2fybU-44",
    "episodeId": "mYVzme2fybU",
    "chunkId": "ck-mYVzme2fybU-44",
    "text": "We should be thinking seriously about lowering the number of hours that people work.",
    "score": 60,
    "num": 44,
    "status": {
      "graph": false,
      "ready": true,
      "verified": false,
      "completed": false,
      "researched": false
    },
    "metadata": {
      "claim": {
        "text": "We should be thinking seriously about lowering the number of hours that people work.",
        "score": 60
      }
    },
    "graph": null,
    "createdAt": "2025-07-02T05:18:22.952Z",
    "updatedAt": "2025-07-02T05:18:22.952Z"
  },
  {
    "id": "ck-mYVzme2fybU-45",
    "episodeId": "mYVzme2fybU",
    "chunkId": "ck-mYVzme2fybU-45",
    "text": "Life expectancy in America is lower than in other major countries, with a four-year shorter lifespan.",
    "score": 85,
    "num": 45,
    "status": {
      "graph": false,
      "ready": true,
      "verified": false,
      "completed": false,
      "researched": false
    },
    "metadata": {
      "claim": {
        "text": "Life expectancy in America is lower than in other major countries, with a four-year shorter lifespan.",
        "score": 85
      }
    },
    "graph": null,
    "createdAt": "2025-07-02T05:18:23.471Z",
    "updatedAt": "2025-07-02T05:18:23.471Z"
  },
  {
    "id": "ck-mYVzme2fybU-46",
    "episodeId": "mYVzme2fybU",
    "chunkId": "ck-mYVzme2fybU-46",
    "text": "People are often unaware of the high sugar content in products like Coca-Cola, such as the 10 teaspoons in a bottle.",
    "score": 75,
    "num": 46,
    "status": {
      "graph": false,
      "ready": true,
      "verified": false,
      "completed": false,
      "researched": false
    },
    "metadata": {
      "claim": {
        "text": "People are often unaware of the high sugar content in products like Coca-Cola, such as the 10 teaspoons in a bottle.",
        "score": 75
      }
    },
    "graph": null,
    "createdAt": "2025-07-02T05:18:23.997Z",
    "updatedAt": "2025-07-02T05:18:23.997Z"
  },
  {
    "id": "ck-mYVzme2fybU-47",
    "episodeId": "mYVzme2fybU",
    "chunkId": "ck-mYVzme2fybU-47",
    "text": "Food manufacturers know exactly that they are causing obesity and God knows what else in kids, leading to diabetes.",
    "score": 80,
    "num": 47,
    "status": {
      "graph": false,
      "ready": true,
      "verified": false,
      "completed": false,
      "researched": false
    },
    "metadata": {
      "claim": {
        "text": "Food manufacturers know exactly that they are causing obesity and God knows what else in kids, leading to diabetes.",
        "score": 80
      }
    },
    "graph": null,
    "createdAt": "2025-07-02T05:18:23.997Z",
    "updatedAt": "2025-07-02T05:18:23.997Z"
  },
  {
    "id": "ck-mYVzme2fybU-48",
    "episodeId": "mYVzme2fybU",
    "chunkId": "ck-mYVzme2fybU-48",
    "text": "Food companies are making different versions of food products for the US and Canada, with the US versions containing harmful dyes.",
    "score": 70,
    "num": 48,
    "status": {
      "graph": false,
      "ready": true,
      "verified": false,
      "completed": false,
      "researched": false
    },
    "metadata": {
      "claim": {
        "text": "Food companies are making different versions of food products for the US and Canada, with the US versions containing harmful dyes.",
        "score": 70
      }
    },
    "graph": null,
    "createdAt": "2025-07-02T05:18:23.472Z",
    "updatedAt": "2025-07-02T05:18:23.472Z"
  },
  {
    "id": "ck-mYVzme2fybU-49",
    "episodeId": "mYVzme2fybU",
    "chunkId": "ck-mYVzme2fybU-49",
    "text": "Automation is happening at a faster pace than anticipated, as warned by Andrew Yang.",
    "score": 70,
    "num": 49,
    "status": {
      "graph": false,
      "ready": true,
      "verified": false,
      "completed": false,
      "researched": false
    },
    "metadata": {
      "claim": {
        "text": "Automation is happening at a faster pace than anticipated, as warned by Andrew Yang.",
        "score": 70
      }
    },
    "graph": null,
    "createdAt": "2025-07-02T05:18:24.108Z",
    "updatedAt": "2025-07-02T05:18:24.108Z"
  },
  {
    "id": "ck-mYVzme2fybU-50",
    "episodeId": "mYVzme2fybU",
    "chunkId": "ck-mYVzme2fybU-50",
    "text": "A Whimo is a driverless automobile, and people like them because they don't have to deal with potentially shifty drivers.",
    "score": 75,
    "num": 50,
    "status": {
      "graph": false,
      "ready": true,
      "verified": false,
      "completed": false,
      "researched": false
    },
    "metadata": {
      "claim": {
        "text": "A Whimo is a driverless automobile, and people like them because they don't have to deal with potentially shifty drivers.",
        "score": 75
      }
    },
    "graph": null,
    "createdAt": "2025-07-02T05:18:25.566Z",
    "updatedAt": "2025-07-02T05:18:25.566Z"
  },
  {
    "id": "ck-mYVzme2fybU-51",
    "episodeId": "mYVzme2fybU",
    "chunkId": "ck-mYVzme2fybU-51",
    "text": "Automation is the enemy of the human being in a functional society where everyone has a task and gets paid.",
    "score": 60,
    "num": 51,
    "status": {
      "graph": false,
      "ready": true,
      "verified": false,
      "completed": false,
      "researched": false
    },
    "metadata": {
      "claim": {
        "text": "Automation is the enemy of the human being in a functional society where everyone has a task and gets paid.",
        "score": 60
      }
    },
    "graph": null,
    "createdAt": "2025-07-02T05:18:28.189Z",
    "updatedAt": "2025-07-02T05:18:28.189Z"
  },
  {
    "id": "ck-mYVzme2fybU-52",
    "episodeId": "mYVzme2fybU",
    "chunkId": "ck-mYVzme2fybU-52",
    "text": "The speaker supports universal basic income and social safety nets, drawing from personal experience with welfare and food stamps.",
    "score": 75,
    "num": 52,
    "status": {
      "graph": false,
      "ready": true,
      "verified": false,
      "completed": false,
      "researched": false
    },
    "metadata": {
      "claim": {
        "text": "The speaker supports universal basic income and social safety nets, drawing from personal experience with welfare and food stamps.",
        "score": 75
      }
    },
    "graph": null,
    "createdAt": "2025-07-02T05:18:27.308Z",
    "updatedAt": "2025-07-02T05:18:27.308Z"
  },
  {
    "id": "ck-mYVzme2fybU-53",
    "episodeId": "mYVzme2fybU",
    "chunkId": "ck-mYVzme2fybU-53",
    "text": "Work gives people purpose, and it is an important part of our lives, shaping their identity.",
    "score": 75,
    "num": 53,
    "status": {
      "graph": false,
      "ready": true,
      "verified": false,
      "completed": false,
      "researched": false
    },
    "metadata": {
      "claim": {
        "text": "Work gives people purpose, and it is an important part of our lives, shaping their identity.",
        "score": 75
      }
    },
    "graph": null,
    "createdAt": "2025-07-02T05:18:28.344Z",
    "updatedAt": "2025-07-02T05:18:28.344Z"
  },
  {
    "id": "ck-mYVzme2fybU-54",
    "episodeId": "mYVzme2fybU",
    "chunkId": "ck-mYVzme2fybU-54",
    "text": "Automation is inevitable, and we must rethink our purpose in life because of it.",
    "score": 60,
    "num": 54,
    "status": {
      "graph": false,
      "ready": true,
      "verified": false,
      "completed": false,
      "researched": false
    },
    "metadata": {
      "claim": {
        "text": "Automation is inevitable, and we must rethink our purpose in life because of it.",
        "score": 60
      }
    },
    "graph": null,
    "createdAt": "2025-07-02T05:18:28.732Z",
    "updatedAt": "2025-07-02T05:18:28.732Z"
  },
  {
    "id": "ck-mYVzme2fybU-55",
    "episodeId": "mYVzme2fybU",
    "chunkId": "ck-mYVzme2fybU-55",
    "text": "If robots replace people, share profits to provide a universal basic income fund, making the corporation more profitable.",
    "score": 60,
    "num": 55,
    "status": {
      "graph": false,
      "ready": true,
      "verified": false,
      "completed": false,
      "researched": false
    },
    "metadata": {
      "claim": {
        "text": "If robots replace people, share profits to provide a universal basic income fund, making the corporation more profitable.",
        "score": 60
      }
    },
    "graph": null,
    "createdAt": "2025-07-02T05:18:28.733Z",
    "updatedAt": "2025-07-02T05:18:28.733Z"
  },
  {
    "id": "ck-mYVzme2fybU-56",
    "episodeId": "mYVzme2fybU",
    "chunkId": "ck-mYVzme2fybU-56",
    "text": "Norway has a huge wealth fund which came from oil and has a trillion dollars in their wealth for a small country.",
    "score": 75,
    "num": 56,
    "status": {
      "graph": false,
      "ready": true,
      "verified": false,
      "completed": false,
      "researched": false
    },
    "metadata": {
      "claim": {
        "text": "Norway has a huge wealth fund which came from oil and has a trillion dollars in their wealth for a small country.",
        "score": 75
      }
    },
    "graph": null,
    "createdAt": "2025-07-02T05:18:28.731Z",
    "updatedAt": "2025-07-02T05:18:28.731Z"
  },
  {
    "id": "ck-mYVzme2fybU-57",
    "episodeId": "mYVzme2fybU",
    "chunkId": "ck-mYVzme2fybU-57",
    "text": "People do not have to hate each other; it's stupid, it's, you don't even know them, that's why you hate them.",
    "score": 75,
    "num": 57,
    "status": {
      "graph": false,
      "ready": true,
      "verified": false,
      "completed": false,
      "researched": false
    },
    "metadata": {
      "claim": {
        "text": "People do not have to hate each other; it's stupid, it's, you don't even know them, that's why you hate them.",
        "score": 75
      }
    },
    "graph": null,
    "createdAt": "2025-07-02T05:18:30.287Z",
    "updatedAt": "2025-07-02T05:18:30.287Z"
  },
  {
    "id": "ck-mYVzme2fybU-58",
    "episodeId": "mYVzme2fybU",
    "chunkId": "ck-mYVzme2fybU-58",
    "text": "The speaker was arrested while protesting segregated housing in Chicago after crossing a police line.",
    "score": 60,
    "num": 58,
    "status": {
      "graph": false,
      "ready": true,
      "verified": false,
      "completed": false,
      "researched": false
    },
    "metadata": {
      "claim": {
        "text": "The speaker was arrested while protesting segregated housing in Chicago after crossing a police line.",
        "score": 60
      }
    },
    "graph": null,
    "createdAt": "2025-07-02T05:18:29.238Z",
    "updatedAt": "2025-07-02T05:18:29.238Z"
  },
  {
    "id": "ck-mYVzme2fybU-59",
    "episodeId": "mYVzme2fybU",
    "chunkId": "ck-mYVzme2fybU-59",
    "text": "They were taken to a place that was not a jail in the city, causing them to fear for their lives.",
    "score": 60,
    "num": 59,
    "status": {
      "graph": false,
      "ready": true,
      "verified": false,
      "completed": false,
      "researched": false
    },
    "metadata": {
      "claim": {
        "text": "They were taken to a place that was not a jail in the city, causing them to fear for their lives.",
        "score": 60
      }
    },
    "graph": null,
    "createdAt": "2025-07-02T05:18:29.239Z",
    "updatedAt": "2025-07-02T05:18:29.239Z"
  },
  {
    "id": "ck-mYVzme2fybU-60",
    "episodeId": "mYVzme2fybU",
    "chunkId": "ck-mYVzme2fybU-60",
    "text": "The nation has made progress in racial relations, women's rights, and gay rights, which is something to be proud of.",
    "score": 75,
    "num": 60,
    "status": {
      "graph": false,
      "ready": true,
      "verified": false,
      "completed": false,
      "researched": false
    },
    "metadata": {
      "claim": {
        "text": "The nation has made progress in racial relations, women's rights, and gay rights, which is something to be proud of.",
        "score": 75
      }
    },
    "graph": null,
    "createdAt": "2025-07-02T05:18:29.762Z",
    "updatedAt": "2025-07-02T05:18:29.762Z"
  },
  {
    "id": "ck-mYVzme2fybU-61",
    "episodeId": "mYVzme2fybU",
    "chunkId": "ck-mYVzme2fybU-61",
    "text": "Hatred should not be evaluated, and it is also the political exploitation of division within a country.",
    "score": 60,
    "num": 61,
    "status": {
      "graph": false,
      "ready": true,
      "verified": false,
      "completed": false,
      "researched": false
    },
    "metadata": {
      "claim": {
        "text": "Hatred should not be evaluated, and it is also the political exploitation of division within a country.",
        "score": 60
      }
    },
    "graph": null,
    "createdAt": "2025-07-02T05:18:32.388Z",
    "updatedAt": "2025-07-02T05:18:32.388Z"
  },
  {
    "id": "ck-mYVzme2fybU-62",
    "episodeId": "mYVzme2fybU",
    "chunkId": "ck-mYVzme2fybU-62",
    "text": "We should not be having wars right now where countries have disagreements, we should bring them to the table.",
    "score": 75,
    "num": 62,
    "status": {
      "graph": false,
      "ready": true,
      "verified": false,
      "completed": false,
      "researched": false
    },
    "metadata": {
      "claim": {
        "text": "We should not be having wars right now where countries have disagreements, we should bring them to the table.",
        "score": 75
      }
    },
    "graph": null,
    "createdAt": "2025-07-02T05:18:34.487Z",
    "updatedAt": "2025-07-02T05:18:34.487Z"
  },
  {
    "id": "ck-mYVzme2fybU-63",
    "episodeId": "mYVzme2fybU",
    "chunkId": "ck-mYVzme2fybU-63",
    "text": "If people are entirely dependent upon the state for universal basic income, the government could pull the plug.",
    "score": 60,
    "num": 63,
    "status": {
      "graph": false,
      "ready": true,
      "verified": false,
      "completed": false,
      "researched": false
    },
    "metadata": {
      "claim": {
        "text": "If people are entirely dependent upon the state for universal basic income, the government could pull the plug.",
        "score": 60
      }
    },
    "graph": null,
    "createdAt": "2025-07-02T05:18:33.432Z",
    "updatedAt": "2025-07-02T05:18:33.432Z"
  },
  {
    "id": "ck-mYVzme2fybU-64",
    "episodeId": "mYVzme2fybU",
    "chunkId": "ck-mYVzme2fybU-64",
    "text": "The United States is really $37 trillion in debt, and people have to adjust and learn to code.",
    "score": 20,
    "num": 64,
    "status": {
      "graph": false,
      "ready": true,
      "verified": false,
      "completed": false,
      "researched": false
    },
    "metadata": {
      "claim": {
        "text": "The United States is really $37 trillion in debt, and people have to adjust and learn to code.",
        "score": 20
      }
    },
    "graph": null,
    "createdAt": "2025-07-02T05:18:33.010Z",
    "updatedAt": "2025-07-02T05:18:33.010Z"
  },
  {
    "id": "ck-mYVzme2fybU-65",
    "episodeId": "mYVzme2fybU",
    "chunkId": "ck-mYVzme2fybU-65",
    "text": "Automation will eliminate jobs for truck drivers, taxi drivers, and Uber drivers, as well as factory workers.",
    "score": 20,
    "num": 65,
    "status": {
      "graph": false,
      "ready": true,
      "verified": false,
      "completed": false,
      "researched": false
    },
    "metadata": {
      "claim": {
        "text": "Automation will eliminate jobs for truck drivers, taxi drivers, and Uber drivers, as well as factory workers.",
        "score": 20
      }
    },
    "graph": null,
    "createdAt": "2025-07-02T05:18:34.488Z",
    "updatedAt": "2025-07-02T05:18:34.488Z"
  },
  {
    "id": "ck-mYVzme2fybU-66",
    "episodeId": "mYVzme2fybU",
    "chunkId": "ck-mYVzme2fybU-66",
    "text": "Universal basic income is not the solution for meaning, according to the speaker in the text.",
    "score": 60,
    "num": 66,
    "status": {
      "graph": false,
      "ready": true,
      "verified": false,
      "completed": false,
      "researched": false
    },
    "metadata": {
      "claim": {
        "text": "Universal basic income is not the solution for meaning, according to the speaker in the text.",
        "score": 60
      }
    },
    "graph": null,
    "createdAt": "2025-07-02T05:18:32.908Z",
    "updatedAt": "2025-07-02T05:18:32.908Z"
  },
  {
    "id": "ck-mYVzme2fybU-67",
    "episodeId": "mYVzme2fybU",
    "chunkId": "ck-mYVzme2fybU-67",
    "text": "Technology replacing human labor in the near future raises questions about the purpose of human life and meaning.",
    "score": 60,
    "num": 67,
    "status": {
      "graph": false,
      "ready": true,
      "verified": false,
      "completed": false,
      "researched": false
    },
    "metadata": {
      "claim": {
        "text": "Technology replacing human labor in the near future raises questions about the purpose of human life and meaning.",
        "score": 60
      }
    },
    "graph": null,
    "createdAt": "2025-07-02T05:18:35.013Z",
    "updatedAt": "2025-07-02T05:18:35.013Z"
  },
  {
    "id": "ck-mYVzme2fybU-68",
    "episodeId": "mYVzme2fybU",
    "chunkId": "ck-mYVzme2fybU-68",
    "text": "The people who own that technology and the corporations who utilize that technology are becoming phenomenally richer.",
    "score": 60,
    "num": 68,
    "status": {
      "graph": false,
      "ready": true,
      "verified": false,
      "completed": false,
      "researched": false
    },
    "metadata": {
      "claim": {
        "text": "The people who own that technology and the corporations who utilize that technology are becoming phenomenally richer.",
        "score": 60
      }
    },
    "graph": null,
    "createdAt": "2025-07-02T05:18:34.644Z",
    "updatedAt": "2025-07-02T05:18:34.644Z"
  },
  {
    "id": "ck-mYVzme2fybU-69",
    "episodeId": "mYVzme2fybU",
    "chunkId": "ck-mYVzme2fybU-69",
    "text": "The government has a monopoly on governing, and they are corrupt and making insane amounts of money through taxes.",
    "score": 20,
    "num": 69,
    "status": {
      "graph": false,
      "ready": true,
      "verified": false,
      "completed": false,
      "researched": false
    },
    "metadata": {
      "claim": {
        "text": "The government has a monopoly on governing, and they are corrupt and making insane amounts of money through taxes.",
        "score": 20
      }
    },
    "graph": null,
    "createdAt": "2025-07-02T05:18:35.014Z",
    "updatedAt": "2025-07-02T05:18:35.014Z"
  },
  {
    "id": "ck-mYVzme2fybU-70",
    "episodeId": "mYVzme2fybU",
    "chunkId": "ck-mYVzme2fybU-70",
    "text": "Some people are corrupt, incompetent, and wasteful, according to the speaker's assessment of them.",
    "score": 60,
    "num": 70,
    "status": {
      "graph": false,
      "ready": true,
      "verified": false,
      "completed": false,
      "researched": false
    },
    "metadata": {
      "claim": {
        "text": "Some people are corrupt, incompetent, and wasteful, according to the speaker's assessment of them.",
        "score": 60
      }
    },
    "graph": null,
    "createdAt": "2025-07-02T05:18:34.489Z",
    "updatedAt": "2025-07-02T05:18:34.489Z"
  },
  {
    "id": "ck-mYVzme2fybU-71",
    "episodeId": "mYVzme2fybU",
    "chunkId": "ck-mYVzme2fybU-71",
    "text": "Workers owning companies leads to a greater sense of purpose and increased productivity due to their stake.",
    "score": 75,
    "num": 71,
    "status": {
      "graph": false,
      "ready": true,
      "verified": false,
      "completed": false,
      "researched": false
    },
    "metadata": {
      "claim": {
        "text": "Workers owning companies leads to a greater sense of purpose and increased productivity due to their stake.",
        "score": 75
      }
    },
    "graph": null,
    "createdAt": "2025-07-02T05:18:37.692Z",
    "updatedAt": "2025-07-02T05:18:37.692Z"
  },
  {
    "id": "ck-mYVzme2fybU-72",
    "episodeId": "mYVzme2fybU",
    "chunkId": "ck-mYVzme2fybU-72",
    "text": "The speaker wants people to take control over their own government and make demands on it.",
    "score": 60,
    "num": 72,
    "status": {
      "graph": false,
      "ready": true,
      "verified": false,
      "completed": false,
      "researched": false
    },
    "metadata": {
      "claim": {
        "text": "The speaker wants people to take control over their own government and make demands on it.",
        "score": 60
      }
    },
    "graph": null,
    "createdAt": "2025-07-02T05:18:38.151Z",
    "updatedAt": "2025-07-02T05:18:38.151Z"
  },
  {
    "id": "ck-mYVzme2fybU-73",
    "episodeId": "mYVzme2fybU",
    "chunkId": "ck-mYVzme2fybU-73",
    "text": "The founding fathers of the United States created a system of checks and balances to prevent absolute power.",
    "score": 85,
    "num": 73,
    "status": {
      "graph": false,
      "ready": true,
      "verified": false,
      "completed": false,
      "researched": false
    },
    "metadata": {
      "claim": {
        "text": "The founding fathers of the United States created a system of checks and balances to prevent absolute power.",
        "score": 85
      }
    },
    "graph": null,
    "createdAt": "2025-07-02T05:18:38.237Z",
    "updatedAt": "2025-07-02T05:18:38.237Z"
  },
  {
    "id": "ck-mYVzme2fybU-74",
    "episodeId": "mYVzme2fybU",
    "chunkId": "ck-mYVzme2fybU-74",
    "text": "Trump's actions, including suing media and challenging Congress, are seen as a move toward authoritarianism.",
    "score": 20,
    "num": 74,
    "status": {
      "graph": false,
      "ready": true,
      "verified": false,
      "completed": false,
      "researched": false
    },
    "metadata": {
      "claim": {
        "text": "Trump's actions, including suing media and challenging Congress, are seen as a move toward authoritarianism.",
        "score": 20
      }
    },
    "graph": null,
    "createdAt": "2025-07-02T05:18:38.153Z",
    "updatedAt": "2025-07-02T05:18:38.153Z"
  },
  {
    "id": "ck-mYVzme2fybU-75",
    "episodeId": "mYVzme2fybU",
    "chunkId": "ck-mYVzme2fybU-75",
    "text": "He is suing CBS for this Kla Harris interview.",
    "score": 20,
    "num": 75,
    "status": {
      "graph": false,
      "ready": true,
      "verified": false,
      "completed": false,
      "researched": false
    },
    "metadata": {
      "claim": {
        "text": "He is suing CBS for this Kla Harris interview.",
        "score": 20
      }
    },
    "graph": null,
    "createdAt": "2025-07-02T05:18:39.765Z",
    "updatedAt": "2025-07-02T05:18:39.765Z"
  },
  {
    "id": "ck-mYVzme2fybU-76",
    "episodeId": "mYVzme2fybU",
    "chunkId": "ck-mYVzme2fybU-76",
    "text": "The De Moine Register, a respected pollster, made a mistake in a poll, showing Trump doing worse than he did.",
    "score": 60,
    "num": 76,
    "status": {
      "graph": false,
      "ready": true,
      "verified": false,
      "completed": false,
      "researched": false
    },
    "metadata": {
      "claim": {
        "text": "The De Moine Register, a respected pollster, made a mistake in a poll, showing Trump doing worse than he did.",
        "score": 60
      }
    },
    "graph": null,
    "createdAt": "2025-07-02T05:18:39.721Z",
    "updatedAt": "2025-07-02T05:18:39.721Z"
  },
  {
    "id": "ck-mYVzme2fybU-77",
    "episodeId": "mYVzme2fybU",
    "chunkId": "ck-mYVzme2fybU-77",
    "text": "Suing media has the impact of intimidating media, and the impact is clearly intimidation.",
    "score": 60,
    "num": 77,
    "status": {
      "graph": false,
      "ready": true,
      "verified": false,
      "completed": false,
      "researched": false
    },
    "metadata": {
      "claim": {
        "text": "Suing media has the impact of intimidating media, and the impact is clearly intimidation.",
        "score": 60
      }
    },
    "graph": null,
    "createdAt": "2025-07-02T05:18:39.874Z",
    "updatedAt": "2025-07-02T05:18:39.874Z"
  },
  {
    "id": "ck-mYVzme2fybU-78",
    "episodeId": "mYVzme2fybU",
    "chunkId": "ck-mYVzme2fybU-78",
    "text": "To get this merger, huge merger, they have to go, guess what? To the federal government.",
    "score": 70,
    "num": 78,
    "status": {
      "graph": false,
      "ready": true,
      "verified": false,
      "completed": false,
      "researched": false
    },
    "metadata": {
      "claim": {
        "text": "To get this merger, huge merger, they have to go, guess what? To the federal government.",
        "score": 70
      }
    },
    "graph": null,
    "createdAt": "2025-07-02T05:18:40.250Z",
    "updatedAt": "2025-07-02T05:18:40.250Z"
  },
  {
    "id": "ck-mYVzme2fybU-79",
    "episodeId": "mYVzme2fybU",
    "chunkId": "ck-mYVzme2fybU-79",
    "text": "I'm going to sue Joe Rogan for $100 million, and he may not talk about those issues in the future.",
    "score": 20,
    "num": 79,
    "status": {
      "graph": false,
      "ready": true,
      "verified": false,
      "completed": false,
      "researched": false
    },
    "metadata": {
      "claim": {
        "text": "I'm going to sue Joe Rogan for $100 million, and he may not talk about those issues in the future.",
        "score": 20
      }
    },
    "graph": null,
    "createdAt": "2025-07-02T05:18:39.834Z",
    "updatedAt": "2025-07-02T05:18:39.834Z"
  },
  {
    "id": "ck-mYVzme2fybU-80",
    "episodeId": "mYVzme2fybU",
    "chunkId": "ck-mYVzme2fybU-80",
    "text": "Americans agree on almost all issues, including better lives, healthcare, education, safer streets, and community.",
    "score": 75,
    "num": 80,
    "status": {
      "graph": false,
      "ready": true,
      "verified": false,
      "completed": false,
      "researched": false
    },
    "metadata": {
      "claim": {
        "text": "Americans agree on almost all issues, including better lives, healthcare, education, safer streets, and community.",
        "score": 75
      }
    },
    "graph": null,
    "createdAt": "2025-07-02T05:18:40.249Z",
    "updatedAt": "2025-07-02T05:18:40.249Z"
  },
  {
    "id": "ck-mYVzme2fybU-81",
    "episodeId": "mYVzme2fybU",
    "chunkId": "ck-mYVzme2fybU-81",
    "text": "The speaker believes that the political divide in the country accentuates the extreme ends of the political spectrum.",
    "score": 60,
    "num": 81,
    "status": {
      "graph": false,
      "ready": true,
      "verified": false,
      "completed": false,
      "researched": false
    },
    "metadata": {
      "claim": {
        "text": "The speaker believes that the political divide in the country accentuates the extreme ends of the political spectrum.",
        "score": 60
      }
    },
    "graph": null,
    "createdAt": "2025-07-02T05:18:42.344Z",
    "updatedAt": "2025-07-02T05:18:42.344Z"
  }
]