{
  "channelId": "UCwWhs_6x42TyRM4Wstoq8HA",
  "channelName": "The Daily Show",
  "channelSlug": "@thedailyshow",
  "channelUrl": "https://www.youtube.com/channel/UCwWhs_6x42TyRM4Wstoq8HA",
  "episodesAnalyzed": 5,
  "claimsAnalyzed": 18,
  "generatedAt": "2025-07-20T11:13:15.866Z",
  "profile": {
    "channelCharacteristics": {
      "contentStyle": "Humorous, satirical, and conversational",
      "expertise": "Popular/Accessible",
      "politicalLeaning": "Left-leaning",
      "primaryTopics": [
        "Politics",
        "Current Events",
        "Social Commentary",
        "Comedy",
        "Technology"
      ],
      "tone": "Humorous and critical"
    },
    "summary": "The Daily Show is a politically-charged comedy podcast that satirizes current events and political figures, primarily focusing on US politics. It features interviews, commentary, and comedic segments, targeting a well-informed audience interested in social and political issues.",
    "targetAudience": {
      "ageRange": "25-55",
      "educationLevel": "College educated or higher",
      "gender": "Mixed, with a slight male skew",
      "interests": [
        "Politics",
        "Current Events",
        "Comedy",
        "Social Justice",
        "Media Criticism"
      ],
      "socioeconomicStatus": "Middle to upper-middle class"
    },
    "uniqueFeatures": {
      "communityEngagement": "High, through social media and guest interactions",
      "differentiators": [
        "Satirical approach to news and politics",
        "Interviews with prominent figures",
        "Focus on both domestic and international issues",
        "Use of humor to critique and inform",
        "Strong brand recognition and legacy"
      ],
      "episodeFormat": "Typically includes a monologue, segments, and interviews, with varying lengths",
      "guestTypes": "Politicians, comedians, journalists, and experts"
    },
    "viewpoints": {
      "approachToTopics": "Critical and satirical, often highlighting hypocrisy and absurdity",
      "controversialStances": [
        "Criticism of conservative politicians and policies",
        "Support for progressive viewpoints",
        "Skepticism towards corporate power and influence"
      ],
      "coreBeliefs": [
        "Importance of critical thinking",
        "Value of social justice and equality",
        "Need for accountability in politics",
        "Power of humor and satire",
        "Importance of informed citizenry"
      ],
      "worldview": "Progressive, with a focus on social justice, political accountability, and the importance of an informed citizenry."
    }
  }
}